alphadia/__init__.py
alphadia/cli.py
alphadia/exceptions.py
alphadia/search_plan.py
alphadia/search_step.py
alphadia/utils.py
alphadia/calibration/__init__.py
alphadia/calibration/estimator.py
alphadia/calibration/models.py
alphadia/calibration/plot.py
alphadia/constants/__init__.py
alphadia/constants/default.yaml
alphadia/constants/default_python.yaml
alphadia/constants/keys.py
alphadia/constants/multistep.yaml
alphadia/constants/settings.py
alphadia/constants/classifier/fa9945ae23db872d.pth
alphadia/fdr/__init__.py
alphadia/fdr/classifiers.py
alphadia/fdr/fdr.py
alphadia/fdr/plotting.py
alphadia/fdr/utils.py
alphadia/fdr/_fdrx/__init__.py
alphadia/fdr/_fdrx/base.py
alphadia/fdr/_fdrx/plotting.py
alphadia/fdr/_fdrx/stats.py
alphadia/fdr/_fdrx/models/__init__.py
alphadia/fdr/_fdrx/models/logistic_regression.py
alphadia/fdr/_fdrx/models/two_step_classifier.py
alphadia/fragcomp/__init__.py
alphadia/fragcomp/fragcomp.py
alphadia/fragcomp/utils.py
alphadia/libtransform/__init__.py
alphadia/libtransform/base.py
alphadia/libtransform/decoy.py
alphadia/libtransform/fasta_digest.py
alphadia/libtransform/flatten.py
alphadia/libtransform/harmonize.py
alphadia/libtransform/loader.py
alphadia/libtransform/mbr.py
alphadia/libtransform/multiplex.py
alphadia/libtransform/prediction.py
alphadia/outputtransform/__init__.py
alphadia/outputtransform/df_builders.py
alphadia/outputtransform/grouping.py
alphadia/outputtransform/outputaccumulator.py
alphadia/outputtransform/protein_fdr.py
alphadia/outputtransform/search_plan_output.py
alphadia/outputtransform/utils.py
alphadia/outputtransform/quantification/__init__.py
alphadia/outputtransform/quantification/fragment_accumulator.py
alphadia/outputtransform/quantification/quant_builder.py
alphadia/outputtransform/quantification/quant_output_builder.py
alphadia/raw_data/__init__.py
alphadia/raw_data/alpharaw_wrapper.py
alphadia/raw_data/bruker.py
alphadia/raw_data/dia_cycle.py
alphadia/reporting/__init__.py
alphadia/reporting/logging.py
alphadia-2.0.3.dist-info/licenses/LICENSE.txt
alphadia-2.0.3.dist-info/METADATA
alphadia-2.0.3.dist-info/WHEEL
alphadia-2.0.3.dist-info/entry_points.txt
alphadia-2.0.3.dist-info/top_level.txt
alphadia-2.0.3.dist-info/RECORD
