Metadata-Version: 2.4
Name: alphadia
Version: 2.0.3
Summary: A novel proteomics search engine for DIA data based on end-to-end transfer learning.
Author-email: Mann Labs <wallmann@biochem.mpg.de>
License:                                  Apache License
Project-URL: repository, https://github.com/MannLabs/alphadia
Project-URL: issues, https://github.com/MannLabs/alphadia/issues
Project-URL: download, https://github.com/MannLabs/alphadia/releases
Project-URL: homepage, https://www.alphapept.org
Project-URL: Mann Labs Homepage, https://www.biochem.mpg.de/mann
Project-URL: publication, https://doi.org/10.1038/s41587-025-02791-w
Project-URL: documentation, https://alphadia.readthedocs.io/en/latest/
Keywords: mass spectrometry,proteomics,search engine,DIA,data-independent acquisition,bioinformatics,AlphaPept,AlphaPept ecosystem,alphapept.org
Classifier: Development Status :: 4 - Beta
Classifier: Intended Audience :: Science/Research
Classifier: License :: OSI Approved :: Apache Software License
Classifier: Operating System :: OS Independent
Classifier: Programming Language :: Python :: 3
Classifier: Topic :: Scientific/Engineering :: Bio-Informatics
Requires-Python: >=3.10.0
License-File: LICENSE.txt
Requires-Dist: alphadia-search-rs<2,>=1
Requires-Dist: alpharaw>=0.3.1
Requires-Dist: alphatims>=1.0.8
Requires-Dist: alphabase>=1.5.0
Requires-Dist: peptdeep>=1.3.0
Requires-Dist: directlfq>=0.2.19
Requires-Dist: quantselect>=0.1.3
Requires-Dist: argparse
Requires-Dist: seaborn
Requires-Dist: rocket_fft
Requires-Dist: xxhash
Requires-Dist: torchmetrics
Requires-Dist: transformers
Requires-Dist: pyarrow>=20.0.0
Requires-Dist: numpy<2
Requires-Dist: scipy==1.12.0
Requires-Dist: llvmlite<0.46.0; sys_platform == "darwin" and platform_machine == "x86_64"
Provides-Extra: stable
Requires-Dist: alphabase==1.7.1; extra == "stable"
Requires-Dist: alphadia-search-rs==1.1.1; extra == "stable"
Requires-Dist: alpharaw==0.4.7; extra == "stable"
Requires-Dist: alphatims==1.0.9; extra == "stable"
Requires-Dist: argparse==1.4.0; extra == "stable"
Requires-Dist: biopython==1.85; extra == "stable"
Requires-Dist: certifi==2025.1.31; extra == "stable"
Requires-Dist: cffi==1.17.1; extra == "stable"
Requires-Dist: charset-normalizer==3.4.1; extra == "stable"
Requires-Dist: click==8.1.8; extra == "stable"
Requires-Dist: clr-loader==0.2.7.post0; extra == "stable"
Requires-Dist: contextlib2==21.6.0; extra == "stable"
Requires-Dist: contourpy==1.3.1; extra == "stable"
Requires-Dist: cycler==0.12.1; extra == "stable"
Requires-Dist: dill==0.3.9; extra == "stable"
Requires-Dist: directlfq==0.3.1; extra == "stable"
Requires-Dist: filelock==3.18.0; extra == "stable"
Requires-Dist: fonttools==4.57.0; extra == "stable"
Requires-Dist: fsspec==2025.3.2; extra == "stable"
Requires-Dist: h5py==3.13.0; extra == "stable"
Requires-Dist: huggingface-hub==0.30.2; extra == "stable"
Requires-Dist: idna==3.10; extra == "stable"
Requires-Dist: jinja2==3.1.6; extra == "stable"
Requires-Dist: joblib==1.4.2; extra == "stable"
Requires-Dist: kiwisolver==1.4.8; extra == "stable"
Requires-Dist: lightning-utilities==0.14.3; extra == "stable"
Requires-Dist: llvmlite==0.44.0; extra == "stable"
Requires-Dist: lxml==5.3.2; extra == "stable"
Requires-Dist: markupsafe==3.0.2; extra == "stable"
Requires-Dist: matplotlib==3.10.1; extra == "stable"
Requires-Dist: mpmath==1.3.0; extra == "stable"
Requires-Dist: multiprocess==0.70.17; extra == "stable"
Requires-Dist: networkx==3.4.2; extra == "stable"
Requires-Dist: numba==0.61.2; extra == "stable"
Requires-Dist: numpy==1.26.4; extra == "stable"
Requires-Dist: nvidia-cublas-cu12==12.4.5.8; sys_platform == "linux" and extra == "stable"
Requires-Dist: nvidia-cuda-cupti-cu12==12.4.127; sys_platform == "linux" and extra == "stable"
Requires-Dist: nvidia-cuda-nvrtc-cu12==12.4.127; sys_platform == "linux" and extra == "stable"
Requires-Dist: nvidia-cuda-runtime-cu12==12.4.127; sys_platform == "linux" and extra == "stable"
Requires-Dist: nvidia-cudnn-cu12==9.1.0.70; sys_platform == "linux" and extra == "stable"
Requires-Dist: nvidia-cufft-cu12==11.2.1.3; sys_platform == "linux" and extra == "stable"
Requires-Dist: nvidia-curand-cu12==10.3.5.147; sys_platform == "linux" and extra == "stable"
Requires-Dist: nvidia-cusolver-cu12==11.6.1.9; sys_platform == "linux" and extra == "stable"
Requires-Dist: nvidia-cusparse-cu12==12.3.1.170; sys_platform == "linux" and extra == "stable"
Requires-Dist: nvidia-cusparselt-cu12==0.6.2; sys_platform == "linux" and extra == "stable"
Requires-Dist: nvidia-nccl-cu12==2.21.5; sys_platform == "linux" and extra == "stable"
Requires-Dist: nvidia-nvjitlink-cu12==12.4.127; sys_platform == "linux" and extra == "stable"
Requires-Dist: nvidia-nvtx-cu12==12.4.127; sys_platform == "linux" and extra == "stable"
Requires-Dist: packaging==24.2; extra == "stable"
Requires-Dist: pandas==2.2.3; extra == "stable"
Requires-Dist: peptdeep==1.3.2; extra == "stable"
Requires-Dist: pillow==11.1.0; extra == "stable"
Requires-Dist: psutil==7.0.0; extra == "stable"
Requires-Dist: pyahocorasick==2.1.0; extra == "stable"
Requires-Dist: pyarrow==20.0.0; extra == "stable"
Requires-Dist: pycparser==2.22; extra == "stable"
Requires-Dist: pyparsing==3.2.3; extra == "stable"
Requires-Dist: pyteomics==4.7.5; extra == "stable"
Requires-Dist: python-dateutil==2.9.0.post0; extra == "stable"
Requires-Dist: pythonnet==3.0.5; extra == "stable"
Requires-Dist: pytz==2025.2; extra == "stable"
Requires-Dist: pyyaml==6.0.2; extra == "stable"
Requires-Dist: pyzstd==0.16.2; extra == "stable"
Requires-Dist: rdkit==2024.9.6; extra == "stable"
Requires-Dist: regex==2024.11.6; extra == "stable"
Requires-Dist: requests==2.32.3; extra == "stable"
Requires-Dist: rocket-fft==0.2.5; extra == "stable"
Requires-Dist: safetensors==0.5.3; extra == "stable"
Requires-Dist: scikit-learn==1.6.1; extra == "stable"
Requires-Dist: scipy==1.12.0; extra == "stable"
Requires-Dist: seaborn==0.13.2; extra == "stable"
Requires-Dist: setuptools==78.1.0; extra == "stable"
Requires-Dist: six==1.17.0; extra == "stable"
Requires-Dist: sympy==1.13.1; extra == "stable"
Requires-Dist: threadpoolctl==3.6.0; extra == "stable"
Requires-Dist: tokenizers==0.21.1; extra == "stable"
Requires-Dist: torch==2.6.0; (sys_platform != "darwin" or platform_machine != "x86_64") and extra == "stable"
Requires-Dist: torchmetrics==1.7.1; extra == "stable"
Requires-Dist: tqdm==4.67.1; extra == "stable"
Requires-Dist: transformers==4.51.2; extra == "stable"
Requires-Dist: triton==3.2.0; sys_platform == "linux" and extra == "stable"
Requires-Dist: typing-extensions==4.13.2; extra == "stable"
Requires-Dist: tzdata==2025.2; extra == "stable"
Requires-Dist: urllib3==2.4.0; extra == "stable"
Requires-Dist: xxhash==3.5.0; extra == "stable"
Requires-Dist: torch==2.2.2; (sys_platform == "darwin" and platform_machine == "x86_64") and extra == "stable"
Provides-Extra: tests
Requires-Dist: coverage; extra == "tests"
Requires-Dist: coverage-badge; extra == "tests"
Requires-Dist: pytest; extra == "tests"
Requires-Dist: nbmake; extra == "tests"
Requires-Dist: uv; extra == "tests"
Provides-Extra: docs
Requires-Dist: sphinx-rtd-theme; extra == "docs"
Requires-Dist: nbsphinx; extra == "docs"
Requires-Dist: myst_parser; extra == "docs"
Requires-Dist: sphinx_design; extra == "docs"
Requires-Dist: furo; extra == "docs"
Requires-Dist: pandoc; extra == "docs"
Provides-Extra: development
Requires-Dist: pre-commit==4.3.0; extra == "development"
Requires-Dist: coverage; extra == "development"
Requires-Dist: coverage-badge; extra == "development"
Requires-Dist: pytest; extra == "development"
Requires-Dist: nbmake; extra == "development"
Requires-Dist: uv; extra == "development"
Requires-Dist: sphinx-rtd-theme; extra == "development"
Requires-Dist: nbsphinx; extra == "development"
Requires-Dist: myst_parser; extra == "development"
Requires-Dist: sphinx_design; extra == "development"
Requires-Dist: furo; extra == "development"
Requires-Dist: pandoc; extra == "development"
Dynamic: license-file
